<?xml version="1.0" encoding="utf-8"?>
<ArrayOfTask xmlns:xsi="http://www.w3.org/2001/XMLSchema-instance" xmlns:xsd="http://www.w3.org/2001/XMLSchema">
  <Task>
    <Id>1004</Id>
    <EngineerId xsi:nil="true" />
    <IsMileston>false</IsMileston>
    <StartDate xsi:nil="true" />
    <DeadlineDate xsi:nil="true" />
    <CompleteDate xsi:nil="true" />
    <ScheduledDate xsi:nil="true" />
    <RequiredEffortTime>PT1H1M1S</RequiredEffortTime>
    <ComplexityLevel>Competent</ComplexityLevel>
    <Description>Planning the appearance of the web page</Description>
    <Alias>first Planing</Alias>
    <CreateAtDate xsi:nil="true" />
  </Task>
  <Task>
    <Id>1005</Id>
    <EngineerId xsi:nil="true" />
    <IsMileston>false</IsMileston>
    <StartDate xsi:nil="true" />
    <DeadlineDate xsi:nil="true" />
    <CompleteDate xsi:nil="true" />
    <ScheduledDate xsi:nil="true" />
    <RequiredEffortTime>P2D</RequiredEffortTime>
    <ComplexityLevel>Proficient</ComplexityLevel>
    <Description>Building a database with appropriate values</Description>
    <Alias>Build database</Alias>
    <CreateAtDate xsi:nil="true" />
  </Task>
  <Task>
    <Id>1006</Id>
    <EngineerId xsi:nil="true" />
    <IsMileston>false</IsMileston>
    <StartDate xsi:nil="true" />
    <DeadlineDate xsi:nil="true" />
    <CompleteDate xsi:nil="true" />
    <ScheduledDate xsi:nil="true" />
    <RequiredEffortTime>P3D</RequiredEffortTime>
    <ComplexityLevel>Expert</ComplexityLevel>
    <Description>Writing server and client code</Description>
    <Alias>Coding</Alias>
    <CreateAtDate xsi:nil="true" />
  </Task>
  <Task>
    <Id>1007</Id>
    <EngineerId xsi:nil="true" />
    <IsMileston>false</IsMileston>
    <StartDate xsi:nil="true" />
    <DeadlineDate xsi:nil="true" />
    <CompleteDate xsi:nil="true" />
    <ScheduledDate xsi:nil="true" />
    <RequiredEffortTime>P4D</RequiredEffortTime>
    <ComplexityLevel>Competent</ComplexityLevel>
    <Description>User page display design and code usage</Description>
    <Alias> Display design</Alias>
    <CreateAtDate xsi:nil="true" />
  </Task>
</ArrayOfTask>